rdstation_client/__init__.py
rdstation_client/errors.py
rdstation_client/utils.py
rdstation_client-0.0.10.dist-info/LICENSE
rdstation_client-0.0.10.dist-info/METADATA
rdstation_client-0.0.10.dist-info/WHEEL
rdstation_client-0.0.10.dist-info/top_level.txt
rdstation_client-0.0.10.dist-info/RECORD
