Metadata-Version: 2.1
Name: rdstation-client
Version: 0.0.10
Summary: Client for access API rdstation.
Home-page: https://github.com/sxslex/rdstation-client
Author: SleX
Author-email: sx.slex@gmail.com
License: UNKNOWN
Download-URL: https://github.com/sxslex/rdstation-client/archive/v0.0.10.tar.gz
Keywords: rdstation,api,client,rd
Platform: UNKNOWN
Classifier: License :: OSI Approved :: GNU General Public License (GPL)
Classifier: Natural Language :: English
Classifier: Operating System :: OS Independent
Classifier: Programming Language :: Python :: 2.7
Classifier: Programming Language :: Python :: 3.5
Classifier: Programming Language :: Python :: 3.6
Classifier: Programming Language :: Python :: 3.7
Classifier: Programming Language :: Python :: 3.8
Classifier: Topic :: Software Development :: Libraries :: Python Modules
